Metadata-Version: 2.1
Name: torchTT
Version: 0.3
Summary: Tensor-Train decomposition in pytorch.
Author-email: Ion Gabriel Ion <ion.ion.gabriel@gmail.com>
License: MIT License
Keywords: pytorch,tensor-train decomposition
Classifier: Programming Language :: Python :: 3
Classifier: License :: OSI Approved :: MIT License
Classifier: Operating System :: OS Independent
Requires-Python: >=3.7
License-File: LICENSE
Requires-Dist: torch>=1.7
Requires-Dist: numpy>=1.18
Requires-Dist: opt_einsum
Requires-Dist: scipy>=0.16
Requires-Dist: ninja
